setup.py
django_addons_formlib/__init__.py
django_addons_formlib/forms.py
django_addons_formlib.egg-info/PKG-INFO
django_addons_formlib.egg-info/SOURCES.txt
django_addons_formlib.egg-info/dependency_links.txt
django_addons_formlib.egg-info/not-zip-safe
django_addons_formlib.egg-info/top_level.txt