Metadata-Version: 1.1
Name: django-addons-formlib
Version: 2.0.1
Summary: django-addons Framework form library
Home-page: https://github.com/django-addons/django-addons-formlib
Author: Divio AG
Author-email: info@divio.ch
License: UNKNOWN
Platform: UNKNOWN
Classifier: Development Status :: 2 - Pre-Alpha
Classifier: Programming Language :: Python :: 3.6
Classifier: Framework :: Django :: 2.0
